langchain_arxiv/__init__.py
langchain_arxiv/__main__.py
langchain_arxiv/cli.py
langchain_arxiv/langchain_arxiv.py
langchain_arxiv/prompts.py
langchain_arxiv/utils.py
langchain_arxiv-0.1.0.dist-info/licenses/LICENSE
langchain_arxiv-0.1.0.dist-info/METADATA
langchain_arxiv-0.1.0.dist-info/WHEEL
langchain_arxiv-0.1.0.dist-info/entry_points.txt
langchain_arxiv-0.1.0.dist-info/top_level.txt
langchain_arxiv-0.1.0.dist-info/RECORD
