Metadata-Version: 2.4
Name: langchain_arxiv
Version: 0.1.0
Summary: Python Boilerplate contains all the boilerplate you need to create a Python package.
Author-email: Druiz35 <druiz35contact@gmail.com>
Maintainer-email: Druiz35 <druiz35contact@gmail.com>
License: MIT
Project-URL: bugs, https://github.com/druiz35/langchain_arxiv/issues
Project-URL: changelog, https://github.com/druiz35/langchain_arxiv/blob/master/changelog.md
Project-URL: homepage, https://github.com/druiz35/langchain_arxiv
Requires-Python: >=3.10
License-File: LICENSE
Requires-Dist: typer
Provides-Extra: test
Requires-Dist: coverage; extra == "test"
Requires-Dist: pytest; extra == "test"
Requires-Dist: ruff; extra == "test"
Requires-Dist: ty; extra == "test"
Requires-Dist: ipdb; extra == "test"
Dynamic: license-file
